jira_2_notion_db/__init__.py
jira_2_notion_db/services/__init__.py
jira_2_notion_db/services/jira_service.py
jira_2_notion_db/services/notion_service.py
jira_2_notion_db/utils/__init__.py
jira_2_notion_db/utils/logger_util.py
jira_2_notion_db-1.1.2.data/scripts/jira-2-notion-db
jira_2_notion_db-1.1.2.dist-info/LICENSE
jira_2_notion_db-1.1.2.dist-info/METADATA
jira_2_notion_db-1.1.2.dist-info/WHEEL
jira_2_notion_db-1.1.2.dist-info/top_level.txt
jira_2_notion_db-1.1.2.dist-info/RECORD
