Metadata-Version: 2.1
Name: jira-2-notion-db
Version: 1.1.2
Summary: Jira to Notion-database Migration Tool
Home-page: https://github.com/minwook-shin/jira-2-notion-db
Author: minwook-shin
Author-email: minwook0106@gmail.com
Project-URL: Bug Tracker, https://github.com/minwook-shin/jira-2-notion-db/issues
Classifier: Programming Language :: Python :: 3
Classifier: License :: OSI Approved :: GNU General Public License v3 (GPLv3)
Classifier: Operating System :: OS Independent
Requires-Python: >=3.7
License-File: LICENSE
Requires-Dist: jira (==3.4.1)
Requires-Dist: notion-database (==20220628.3)
